vsco_api/__init__.py
vsco_api/_vsco.py
vsco_api-0.2.1.dist-info/METADATA
vsco_api-0.2.1.dist-info/WHEEL
vsco_api-0.2.1.dist-info/RECORD
